PyCyberGear/__init__.py
PyCyberGear/shell/__init__.py
PyCyberGear/shell/usage.py
PyCyberGear/src/temp.txt
PyCyberGear-0.0.1.dist-info/LICENSE
PyCyberGear-0.0.1.dist-info/METADATA
PyCyberGear-0.0.1.dist-info/WHEEL
PyCyberGear-0.0.1.dist-info/entry_points.txt
PyCyberGear-0.0.1.dist-info/top_level.txt
PyCyberGear-0.0.1.dist-info/zip-safe
PyCyberGear-0.0.1.dist-info/RECORD
