Metadata-Version: 2.1
Name: PyCyberGear
Version: 0.0.1
Summary: project description
Home-page: 
Author: HaveTwoBrush
Author-email: kinggreenhall@163.com
License: MIT License
Classifier: Programming Language :: Python :: 3
Classifier: License :: OSI Approved :: MIT License
Classifier: Operating System :: OS Independent
Requires-Python: >=3.6
License-File: LICENSE
